ripplex/__init__.py
ripplex/core/__init__.py
ripplex/core/context.py
ripplex/core/debug.py
ripplex/core/flow.py
ripplex/core/loop.py
ripplex-1.0.0.dist-info/METADATA
ripplex-1.0.0.dist-info/WHEEL
ripplex-1.0.0.dist-info/licenses/LICENSE
ripplex-1.0.0.dist-info/RECORD
