Metadata-Version: 2.4
Name: ripplex
Version: 1.0.0
Summary: A Python framework for parallel execution with automatic dependency resolution and variable capture.
Project-URL: Homepage, https://github.com/sethburkart/ripplex
Project-URL: Repository, https://github.com/sethburkart/ripplex
Project-URL: Issues, https://github.com/sethburkart/ripplex/issues
Project-URL: Documentation, https://github.com/sethburkart/ripplex#readme
Author-email: Seth Burkart <sethburkart7@gmail.com>
License-Expression: MIT
License-File: LICENSE
Keywords: async,concurrency,flow,parallel,threading
Classifier: Development Status :: 4 - Beta
Classifier: Intended Audience :: Developers
Classifier: License :: OSI Approved :: MIT License
Classifier: Programming Language :: Python :: 3
Classifier: Programming Language :: Python :: 3.8
Classifier: Programming Language :: Python :: 3.9
Classifier: Programming Language :: Python :: 3.10
Classifier: Programming Language :: Python :: 3.11
Classifier: Programming Language :: Python :: 3.12
Classifier: Topic :: Software Development :: Libraries :: Python Modules
Classifier: Topic :: System :: Distributed Computing
Requires-Python: >=3.8
Requires-Dist: rich>=13.0.0
Provides-Extra: dev
Requires-Dist: black>=22.0.0; extra == 'dev'
Requires-Dist: mypy>=1.0.0; extra == 'dev'
Requires-Dist: pytest-cov>=4.0.0; extra == 'dev'
Requires-Dist: pytest>=7.0.0; extra == 'dev'
Requires-Dist: ruff>=0.1.0; extra == 'dev'
